mil_benchmarks/__init__.py
mil_benchmarks/absence.py
mil_benchmarks/complex.py
mil_benchmarks/presence.py
mil_benchmarks/standard.py
mil_benchmarks/utils.py
mil_benchmarks/csvs/__init__.py
mil_benchmarks/csvs/absence/__init__.py
mil_benchmarks/csvs/absence/cifar10/01_test.csv
mil_benchmarks/csvs/absence/cifar10/01_train.csv
mil_benchmarks/csvs/absence/cifar10/12_test.csv
mil_benchmarks/csvs/absence/cifar10/12_train.csv
mil_benchmarks/csvs/absence/cifar10/23_test.csv
mil_benchmarks/csvs/absence/cifar10/23_train.csv
mil_benchmarks/csvs/absence/cifar10/34_test.csv
mil_benchmarks/csvs/absence/cifar10/34_train.csv
mil_benchmarks/csvs/absence/cifar10/45_test.csv
mil_benchmarks/csvs/absence/cifar10/45_train.csv
mil_benchmarks/csvs/absence/cifar10/56_test.csv
mil_benchmarks/csvs/absence/cifar10/56_train.csv
mil_benchmarks/csvs/absence/cifar10/67_test.csv
mil_benchmarks/csvs/absence/cifar10/67_train.csv
mil_benchmarks/csvs/absence/cifar10/78_test.csv
mil_benchmarks/csvs/absence/cifar10/78_train.csv
mil_benchmarks/csvs/absence/cifar10/89_test.csv
mil_benchmarks/csvs/absence/cifar10/89_train.csv
mil_benchmarks/csvs/absence/cifar10/__init__.py
mil_benchmarks/csvs/absence/fashion/01_test.csv
mil_benchmarks/csvs/absence/fashion/01_train.csv
mil_benchmarks/csvs/absence/fashion/12_test.csv
mil_benchmarks/csvs/absence/fashion/12_train.csv
mil_benchmarks/csvs/absence/fashion/23_test.csv
mil_benchmarks/csvs/absence/fashion/23_train.csv
mil_benchmarks/csvs/absence/fashion/34_test.csv
mil_benchmarks/csvs/absence/fashion/34_train.csv
mil_benchmarks/csvs/absence/fashion/45_test.csv
mil_benchmarks/csvs/absence/fashion/45_train.csv
mil_benchmarks/csvs/absence/fashion/56_test.csv
mil_benchmarks/csvs/absence/fashion/56_train.csv
mil_benchmarks/csvs/absence/fashion/67_test.csv
mil_benchmarks/csvs/absence/fashion/67_train.csv
mil_benchmarks/csvs/absence/fashion/78_test.csv
mil_benchmarks/csvs/absence/fashion/78_train.csv
mil_benchmarks/csvs/absence/fashion/89_test.csv
mil_benchmarks-0.0.2.dist-info/LICENSE
mil_benchmarks-0.0.2.dist-info/METADATA
mil_benchmarks-0.0.2.dist-info/WHEEL
mil_benchmarks-0.0.2.dist-info/top_level.txt
mil_benchmarks-0.0.2.dist-info/RECORD
