Metadata-Version: 2.1
Name: mil-benchmarks
Version: 0.0.2
Summary: Multiple instance learning benchmarks
Home-page: https://github.com/dgrahn/mil-benchmarks
Author: Dan Grahn
Author-email: dan.grahn@wright.edu
License: UNKNOWN
Platform: UNKNOWN
Classifier: Programming Language :: Python :: 3
Classifier: License :: OSI Approved :: MIT License
Classifier: Operating System :: OS Independent
Requires-Python: >=3.7
Requires-Dist: numpy (>=1.19)
Requires-Dist: pandas (>=1.2)
Requires-Dist: tensorflow (>=2.4)
